odoo/addons/crm_sale_order_line_contract/__init__.py
odoo/addons/crm_sale_order_line_contract/__manifest__.py
odoo/addons/crm_sale_order_line_contract/models/__init__.py
odoo/addons/crm_sale_order_line_contract/models/crm_lead.py
odoo/addons/crm_sale_order_line_contract/models/crm_sale_order_line.py
odoo/addons/crm_sale_order_line_contract/models/sale_order.py
odoo/addons/crm_sale_order_line_contract/models/sale_order_line.py
odoo/addons/crm_sale_order_line_contract/security/ir.model.access.csv
odoo/addons/crm_sale_order_line_contract/views/crm_lead.xml
odoo/addons/crm_sale_order_line_contract/views/sale_order.xml
odoo12_addon_crm_sale_order_line_contract-12.0.0.0.3.dist-info/METADATA
odoo12_addon_crm_sale_order_line_contract-12.0.0.0.3.dist-info/WHEEL
odoo12_addon_crm_sale_order_line_contract-12.0.0.0.3.dist-info/top_level.txt
odoo12_addon_crm_sale_order_line_contract-12.0.0.0.3.dist-info/RECORD
